mimerender.py
mimerender_pr36-0.0.2.dist-info/LICENSE
mimerender_pr36-0.0.2.dist-info/METADATA
mimerender_pr36-0.0.2.dist-info/WHEEL
mimerender_pr36-0.0.2.dist-info/top_level.txt
mimerender_pr36-0.0.2.dist-info/RECORD
