Metadata-Version: 2.1
Name: mimerender-pr36
Version: 0.0.2
Summary: RESTful HTTP Content Negotiation for Flask, Bottle, web.py and webapp2 (Google App Engine)
Home-page: https://github.com/martinblech/mimerender
Author: Martin Blech
Author-email: martinblech@gmail.com
Maintainer: Patrick Huck
Maintainer-email: phuck@lbl.gov
License: MIT
Platform: all
Classifier: Development Status :: 5 - Production/Stable
Classifier: Environment :: Web Environment
Classifier: Intended Audience :: Developers
Classifier: License :: OSI Approved :: MIT License
Classifier: Operating System :: OS Independent
Classifier: Programming Language :: Python
Classifier: Programming Language :: Python :: 2.6
Classifier: Programming Language :: Python :: 2.7
Classifier: Programming Language :: Python :: 3
Classifier: Topic :: Internet :: WWW/HTTP :: Dynamic Content
Requires: python_mimeparse (>=0.1.4)
Requires-Dist: python-mimeparse (>=0.1.4)
